LICENSE.txt
MANIFEST.in
README.md
setup.cfg
setup.py
sermetric/__init__.py
sermetric/metrics.py
sermetric.egg-info/PKG-INFO
sermetric.egg-info/SOURCES.txt
sermetric.egg-info/dependency_links.txt
sermetric.egg-info/requires.txt
sermetric.egg-info/top_level.txt